[
	{
		"key": 1,
		"value": "Anjali"
	},
	{
		"key": 2,
		"value": "Joey"
	},
	{
		"key": 3,
		"value": "Chedro"
	},
	{
		"key": 4,
		"value": "Jennifer"
	},
	{
		"key": 5,
		"value": "Julie"
	},
	{
		"key": 6,
		"value": "Shanker"
	},
	{
		"key": 7,
		"value": "Antony"
	},
	{
		"key": 8,
		"value": "Muhammad"
	},
	{
		"key": 9,
		"value": "Andrew"
	},
	{
		"key": 10,
		"value": "Austin"
	},
	{
		"key": 11,
		"value": "Christopher"
	},
	{
		"key": 12,
		"value": "David"
	},
	{
		"key": 13,
		"value": "Jay"
	},
	{
		"key": 14,
		"value": "Jessica"
	},
	{
		"key": 15,
		"value": "Krishna"
	},
	{
		"key": 16,
		"value": "Kris"
	},
	{
		"key": 17,
		"value": "Phillip"
	},
	{
		"key": 18,
		"value": "Tommy"
	},
	{
		"key": 19,
		"value": "Tyler"
	},
	{
		"key": 20,
		"value": "Zachary"
	},
	{
		"key": 21,
		"value": "Cole"
	},
	{
		"key": 22,
		"value": "Steven"
	},
	{
		"key": 23,
		"value": "Pryde"
	},
	{
		"key": 24,
		"value": "Ana"
	},
	{
		"key": 25,
		"value": "Ian"
	},
	{
		"key": 26,
		"value": "Mariana"
	}
]